Workbook

Sheet Legend
A1: HR TALENT COORDINATOR — OPERATING TOOLKIT
A2: Companion workbook to the hr-talent-coordinator agent. One tab per lifecycle phase.
A4: HOW TO USE
A5: Blue text | B5: Cells you type into. Every blue cell is an input.
A6: Black text | B6: Formulas. Do not overwrite — they recalculate from your inputs.
A7: Yellow fill | B7: Key control cells (e.g. the new hire's start date) that drive other tabs.
A8: Grey italic row | B8: EXAMPLE row showing the expected format. Delete it before real use.
A10: TABS
A11: Reqs | B11: Phase 1 — open requisitions, aging, pipeline depth. The master list; Candidates keys to it.
A12: Candidates | B12: Phase 2 — one row per candidate per req. Stage aging and next-action ownership.
A13: Scorecard | B13: Phase 2 — structured interview rubric. One block per candidate, 1–4 per competency.
A14: Offers | B14: Phase 3 — offers out, acceptance deadlines, contingency status.
A15: Onboarding | B15: Phase 3 — checklist driven off the start date in cell B2. Change B2, all due dates move.
A16: Timekeeping | B16: Phase 4 — daily exception log. Nothing rides to payroll close uncorrected.
A17: ERLog | B17: Phase 4 — employee relations intake. Facts only, plus routing/escalation.
A18: KPIs | B18: Phase 5 — recruiting scorecard. Every metric carries an owner and an action.
A19: Compliance | B19: Phase 5 — filing and posting calendar with days-until countdown.
A20: Restricted | B20: Compensation and background-check status. Segregated on purpose — do not merge into other tabs.
A22: DATA HANDLING RULES
A23: Segregation | B23: I-9s, medical/ADA/leave records, and background results live in separate files from the personnel file. Never merge them.
A24: Restricted fields | B24: Salary, offer amounts, background status, performance ratings and ER content stay off shared tabs.
A25: Screening criteria | B25: Only documented, job-related requirements. No age, DOB, graduation year, photo, gender, family status, national origin, religion, disability, or (pre-conditional-offer) criminal history.
A26: Legal thresholds | B26: Deadlines, form versions and filing dates change. Verify current requirements before relying on any date in the Compliance tab.
A27: Escalation | B27: Harassment, discrimination, retaliation, wage-and-hour, accommodation/leave, terminations and adverse action go to HRBP / Employment Counsel — do not resolve in this workbook.

Sheet Reqs
A1: PHASE 1 — REQUISITION PIPELINE
A2: Blue = input. Days Open, Aging Flag, In Pipeline and Offers Out are formulas.
A4: Req ID | B4: Role | C4: Dept | D4: Location | E4: Type | F4: FLSA | G4: Hiring Manager | H4: Reason | I4: Approved Range | J4: Posted Date | K4: Target Start | L4: Status | M4: Days Open | N4: Aging Flag | O4: In Pipeline | P4: Offers Out | Q4: Notes
A5: REQ-1041 | B5: Warehouse Supervisor | C5: Distribution | D5: Memphis DC | E5: FT | F5: Non-exempt | G5: A. Reyes | H5: Backfill | I5: $58k–$66k | J5: 46237 | K5: 46279 | L5: Interviewing | M5: =IF($J5="","",TODAY()-$J5) | N5: =IF($J5="","",IF($M5>45,"RED >45d",IF($M5>30,"AMBER >30d","OK"))) | O5: =IF($A5="","",COUNTIFS(Candidates!$B$5:$B$64,$A5,Candidates!$M$5:$M$64,"")) | P5: =IF($A5="","",COUNTIFS(Offers!$B$5:$B$44,$A5)) | Q5: EXAMPLE ROW — delete before use
M6: =IF($J6="","",TODAY()-$J6) | N6: =IF($J6="","",IF($M6>45,"RED >45d",IF($M6>30,"AMBER >30d","OK"))) | O6: =IF($A6="","",COUNTIFS(Candidates!$B$5:$B$64,$A6,Candidates!$M$5:$M$64,"")) | P6: =IF($A6="","",COUNTIFS(Offers!$B$5:$B$44,$A6))
M7: =IF($J7="","",TODAY()-$J7) | N7: =IF($J7="","",IF($M7>45,"RED >45d",IF($M7>30,"AMBER >30d","OK"))) | O7: =IF($A7="","",COUNTIFS(Candidates!$B$5:$B$64,$A7,Candidates!$M$5:$M$64,"")) | P7: =IF($A7="","",COUNTIFS(Offers!$B$5:$B$44,$A7))
M8: =IF($J8="","",TODAY()-$J8) | N8: =IF($J8="","",IF($M8>45,"RED >45d",IF($M8>30,"AMBER >30d","OK"))) | O8: =IF($A8="","",COUNTIFS(Candidates!$B$5:$B$64,$A8,Candidates!$M$5:$M$64,"")) | P8: =IF($A8="","",COUNTIFS(Offers!$B$5:$B$44,$A8))
M9: =IF($J9="","",TODAY()-$J9) | N9: =IF($J9="","",IF($M9>45,"RED >45d",IF($M9>30,"AMBER >30d","OK"))) | O9: =IF($A9="","",COUNTIFS(Candidates!$B$5:$B$64,$A9,Candidates!$M$5:$M$64,"")) | P9: =IF($A9="","",COUNTIFS(Offers!$B$5:$B$44,$A9))
M10: =IF($J10="","",TODAY()-$J10) | N10: =IF($J10="","",IF($M10>45,"RED >45d",IF($M10>30,"AMBER >30d","OK"))) | O10: =IF($A10="","",COUNTIFS(Candidates!$B$5:$B$64,$A10,Candidates!$M$5:$M$64,"")) | P10: =IF($A10="","",COUNTIFS(Offers!$B$5:$B$44,$A10))
M11: =IF($J11="","",TODAY()-$J11) | N11: =IF($J11="","",IF($M11>45,"RED >45d",IF($M11>30,"AMBER >30d","OK"))) | O11: =IF($A11="","",COUNTIFS(Candidates!$B$5:$B$64,$A11,Candidates!$M$5:$M$64,"")) | P11: =IF($A11="","",COUNTIFS(Offers!$B$5:$B$44,$A11))
M12: =IF($J12="","",TODAY()-$J12) | N12: =IF($J12="","",IF($M12>45,"RED >45d",IF($M12>30,"AMBER >30d","OK"))) | O12: =IF($A12="","",COUNTIFS(Candidates!$B$5:$B$64,$A12,Candidates!$M$5:$M$64,"")) | P12: =IF($A12="","",COUNTIFS(Offers!$B$5:$B$44,$A12))
M13: =IF($J13="","",TODAY()-$J13) | N13: =IF($J13="","",IF($M13>45,"RED >45d",IF($M13>30,"AMBER >30d","OK"))) | O13: =IF($A13="","",COUNTIFS(Candidates!$B$5:$B$64,$A13,Candidates!$M$5:$M$64,"")) | P13: =IF($A13="","",COUNTIFS(Offers!$B$5:$B$44,$A13))
M14: =IF($J14="","",TODAY()-$J14) | N14: =IF($J14="","",IF($M14>45,"RED >45d",IF($M14>30,"AMBER >30d","OK"))) | O14: =IF($A14="","",COUNTIFS(Candidates!$B$5:$B$64,$A14,Candidates!$M$5:$M$64,"")) | P14: =IF($A14="","",COUNTIFS(Offers!$B$5:$B$44,$A14))
M15: =IF($J15="","",TODAY()-$J15) | N15: =IF($J15="","",IF($M15>45,"RED >45d",IF($M15>30,"AMBER >30d","OK"))) | O15: =IF($A15="","",COUNTIFS(Candidates!$B$5:$B$64,$A15,Candidates!$M$5:$M$64,"")) | P15: =IF($A15="","",COUNTIFS(Offers!$B$5:$B$44,$A15))
M16: =IF($J16="","",TODAY()-$J16) | N16: =IF($J16="","",IF($M16>45,"RED >45d",IF($M16>30,"AMBER >30d","OK"))) | O16: =IF($A16="","",COUNTIFS(Candidates!$B$5:$B$64,$A16,Candidates!$M$5:$M$64,"")) | P16: =IF($A16="","",COUNTIFS(Offers!$B$5:$B$44,$A16))
M17: =IF($J17="","",TODAY()-$J17) | N17: =IF($J17="","",IF($M17>45,"RED >45d",IF($M17>30,"AMBER >30d","OK"))) | O17: =IF($A17="","",COUNTIFS(Candidates!$B$5:$B$64,$A17,Candidates!$M$5:$M$64,"")) | P17: =IF($A17="","",COUNTIFS(Offers!$B$5:$B$44,$A17))
... M44: =IF($J44="","",TODAY()-$J44) | N44: =IF($J44="","",IF($M44>45,"RED >45d",IF($M44>30,"AMBER >30d","OK"))) | O44: =IF($A44="","",COUNTIFS(Candidates!$B$5:$B$64,$A44,Candidates!$M$5:$M$64,"")) | P44: =IF($A44="","",COUNTIFS(Offers!$B$5:$B$44,$A44))

Sheet Candidates
A1: PHASE 2 — CANDIDATE PIPELINE
A2: Restricted fields (comp expectations, background status) belong on the Restricted tab, not here.
A4: Cand ID | B4: Req ID | C4: Candidate | D4: Source | E4: Stage | F4: Stage Entry | G4: Days in Stage | H4: Aging Flag | I4: Last Contact | J4: Next Action | K4: Owner | L4: Next Action Due | M4: Disposition | N4: Reason Code | O4: Notes
A5: C-2207 | B5: REQ-1041 | C5: J. Okafor | D5: Employee referral | E5: Onsite Loop | F5: 46244 | G5: =IF($F5="","",TODAY()-$F5) | H5: =IF($F5="","",IF($M5<>"","Closed",IF($G5>10,"RED >10d",IF($G5>5,"AMBER >5d","OK")))) | I5: 46246 | J5: Schedule panel debrief | K5: J. Pa | L5: 46252 | O5: EXAMPLE ROW — delete before use
G6: =IF($F6="","",TODAY()-$F6) | H6: =IF($F6="","",IF($M6<>"","Closed",IF($G6>10,"RED >10d",IF($G6>5,"AMBER >5d","OK"))))
G7: =IF($F7="","",TODAY()-$F7) | H7: =IF($F7="","",IF($M7<>"","Closed",IF($G7>10,"RED >10d",IF($G7>5,"AMBER >5d","OK"))))
G8: =IF($F8="","",TODAY()-$F8) | H8: =IF($F8="","",IF($M8<>"","Closed",IF($G8>10,"RED >10d",IF($G8>5,"AMBER >5d","OK"))))
G9: =IF($F9="","",TODAY()-$F9) | H9: =IF($F9="","",IF($M9<>"","Closed",IF($G9>10,"RED >10d",IF($G9>5,"AMBER >5d","OK"))))
G10: =IF($F10="","",TODAY()-$F10) | H10: =IF($F10="","",IF($M10<>"","Closed",IF($G10>10,"RED >10d",IF($G10>5,"AMBER >5d","OK"))))
G11: =IF($F11="","",TODAY()-$F11) | H11: =IF($F11="","",IF($M11<>"","Closed",IF($G11>10,"RED >10d",IF($G11>5,"AMBER >5d","OK"))))
G12: =IF($F12="","",TODAY()-$F12) | H12: =IF($F12="","",IF($M12<>"","Closed",IF($G12>10,"RED >10d",IF($G12>5,"AMBER >5d","OK"))))
G13: =IF($F13="","",TODAY()-$F13) | H13: =IF($F13="","",IF($M13<>"","Closed",IF($G13>10,"RED >10d",IF($G13>5,"AMBER >5d","OK"))))
G14: =IF($F14="","",TODAY()-$F14) | H14: =IF($F14="","",IF($M14<>"","Closed",IF($G14>10,"RED >10d",IF($G14>5,"AMBER >5d","OK"))))
G15: =IF($F15="","",TODAY()-$F15) | H15: =IF($F15="","",IF($M15<>"","Closed",IF($G15>10,"RED >10d",IF($G15>5,"AMBER >5d","OK"))))
G16: =IF($F16="","",TODAY()-$F16) | H16: =IF($F16="","",IF($M16<>"","Closed",IF($G16>10,"RED >10d",IF($G16>5,"AMBER >5d","OK"))))
G17: =IF($F17="","",TODAY()-$F17) | H17: =IF($F17="","",IF($M17<>"","Closed",IF($G17>10,"RED >10d",IF($G17>5,"AMBER >5d","OK"))))
... G64: =IF($F64="","",TODAY()-$F64) | H64: =IF($F64="","",IF($M64<>"","Closed",IF($G64>10,"RED >10d",IF($G64>5,"AMBER >5d","OK"))))

Sheet Scorecard
A1: PHASE 2 — STRUCTURED INTERVIEW SCORECARD
A2: One row per competency per interviewer. A rating with no written evidence is not a valid rating.
A4: Candidate | B4: Req ID | C4: Stage | D4: Interviewer | E4: Competency | F4: Rating (1-4) | G4: Behavioral Evidence (required) | H4: Follow-up Needed | J4: RATING SCALE
A5: J. Okafor | B5: REQ-1041 | C5: Onsite Loop | D5: M. Chen | E5: Safety leadership | F5: 3 | G5: Ran daily pre-shift safety huddles; cut recordables from 6 to 2 over 12 months. Named the specific controls. | H5: Probe on incident investigation ownership | J5: 4 — Strong evidence, exceeds the bar for the level
A6: J. Okafor | B6: REQ-1041 | C6: Onsite Loop | D6: M. Chen | E6: Throughput / WMS fluency | F6: 2 | G6: Familiar with Manhattan WMS reporting but has not owned labor-standard setting. | H6: Confirm scope with prior manager reference | J6: 3 — Meets the bar; evidence is concrete and job-related
A7: EXAMPLE BLOCK ABOVE — delete before use | J7: 2 — Partial evidence or gap against a documented must-have
J8: 1 — No evidence, or evidence contradicts the requirement
J10: Rate against the job description only. 'Culture fit' is not a competency —
J11: restate it as a named, observable working-style requirement or drop it.

Sheet Offers
A1: PHASE 3 — OFFER TRACKER
A2: Offer amounts live on the Restricted tab. Background checks run only after a conditional offer.
A4: Candidate | B4: Req ID | C4: Offer Sent | D4: Acceptance Deadline | E4: Days to Deadline | F4: Deadline Flag | G4: Status | H4: Background Check | I4: Right-to-Work Scheduled | J4: References | K4: Start Date | L4: Onboarding Triggered | M4: Approver | N4: Notes
A5: J. Okafor | B5: REQ-1041 | C5: 46248 | D5: 46253 | E5: =IF($D5="","",$D5-TODAY()) | F5: =IF($D5="","",IF($G5="Accepted","Closed",IF($E5<0,"EXPIRED",IF($E5<=1,"FOLLOW UP TODAY","OK")))) | G5: Extended | H5: Pending | I5: Scheduled day 1 | J5: Cleared | K5: 46279 | L5: No | M5: A. Reyes | N5: EXAMPLE ROW — delete before use
E6: =IF($D6="","",$D6-TODAY()) | F6: =IF($D6="","",IF($G6="Accepted","Closed",IF($E6<0,"EXPIRED",IF($E6<=1,"FOLLOW UP TODAY","OK"))))
E7: =IF($D7="","",$D7-TODAY()) | F7: =IF($D7="","",IF($G7="Accepted","Closed",IF($E7<0,"EXPIRED",IF($E7<=1,"FOLLOW UP TODAY","OK"))))
E8: =IF($D8="","",$D8-TODAY()) | F8: =IF($D8="","",IF($G8="Accepted","Closed",IF($E8<0,"EXPIRED",IF($E8<=1,"FOLLOW UP TODAY","OK"))))
E9: =IF($D9="","",$D9-TODAY()) | F9: =IF($D9="","",IF($G9="Accepted","Closed",IF($E9<0,"EXPIRED",IF($E9<=1,"FOLLOW UP TODAY","OK"))))
E10: =IF($D10="","",$D10-TODAY()) | F10: =IF($D10="","",IF($G10="Accepted","Closed",IF($E10<0,"EXPIRED",IF($E10<=1,"FOLLOW UP TODAY","OK"))))
E11: =IF($D11="","",$D11-TODAY()) | F11: =IF($D11="","",IF($G11="Accepted","Closed",IF($E11<0,"EXPIRED",IF($E11<=1,"FOLLOW UP TODAY","OK"))))
E12: =IF($D12="","",$D12-TODAY()) | F12: =IF($D12="","",IF($G12="Accepted","Closed",IF($E12<0,"EXPIRED",IF($E12<=1,"FOLLOW UP TODAY","OK"))))
E13: =IF($D13="","",$D13-TODAY()) | F13: =IF($D13="","",IF($G13="Accepted","Closed",IF($E13<0,"EXPIRED",IF($E13<=1,"FOLLOW UP TODAY","OK"))))
E14: =IF($D14="","",$D14-TODAY()) | F14: =IF($D14="","",IF($G14="Accepted","Closed",IF($E14<0,"EXPIRED",IF($E14<=1,"FOLLOW UP TODAY","OK"))))
E15: =IF($D15="","",$D15-TODAY()) | F15: =IF($D15="","",IF($G15="Accepted","Closed",IF($E15<0,"EXPIRED",IF($E15<=1,"FOLLOW UP TODAY","OK"))))
E16: =IF($D16="","",$D16-TODAY()) | F16: =IF($D16="","",IF($G16="Accepted","Closed",IF($E16<0,"EXPIRED",IF($E16<=1,"FOLLOW UP TODAY","OK"))))
E17: =IF($D17="","",$D17-TODAY()) | F17: =IF($D17="","",IF($G17="Accepted","Closed",IF($E17<0,"EXPIRED",IF($E17<=1,"FOLLOW UP TODAY","OK"))))
... E44: =IF($D44="","",$D44-TODAY()) | F44: =IF($D44="","",IF($G44="Accepted","Closed",IF($E44<0,"EXPIRED",IF($E44<=1,"FOLLOW UP TODAY","OK"))))

Sheet Onboarding
A1: PHASE 3 — ONBOARDING CHECKLIST
A2: New hire: | B2: J. Okafor (EXAMPLE) | C2: Start date: | D2: 46279 | E2: Change D2 and every due date below recalculates.
A4: Phase | B4: Task | C4: Owner | D4: Offset (days from start) | E4: Due Date | F4: Status | G4: Blocker / Note
A5: Pre-start | B5: Offer accepted — notify hiring manager, close req, disposition remaining candidates | C5: Coordinator | D5: -30 | E5: =IF(OR($D$2="",$D5=""),"",$D$2+$D5)
A6: Pre-start | B6: Background check / conditional contingencies cleared and documented | C6: Coordinator | D6: -21 | E6: =IF(OR($D$2="",$D6=""),"",$D$2+$D6)
A7: Pre-start | B7: Welcome email + onboarding portal access sent | C7: Coordinator | D7: -14 | E7: =IF(OR($D$2="",$D7=""),"",$D$2+$D7)
A8: Pre-start | B8: New-hire paperwork packet issued (tax forms, direct deposit, policy acks) | C8: Coordinator | D8: -14 | E8: =IF(OR($D$2="",$D8=""),"",$D$2+$D8)
A9: Pre-start | B9: Employee completes Section 1 of employment-eligibility form (on or before day 1) | C9: New hire | D9: -1 | E9: =IF(OR($D$2="",$D9=""),"",$D$2+$D9)
A10: Pre-start | B10: Equipment, uniform, PPE and badge requested | C10: Coordinator | D10: -10 | E10: =IF(OR($D$2="",$D10=""),"",$D$2+$D10)
A11: Pre-start | B11: IT accounts, systems access and licenses provisioned | C11: IT | D11: -7 | E11: =IF(OR($D$2="",$D11=""),"",$D$2+$D11)
A12: Pre-start | B12: Payroll/HRIS record created — pay rate audited against the signed offer letter | C12: Coordinator | D12: -7 | E12: =IF(OR($D$2="",$D12=""),"",$D$2+$D12)
A13: Pre-start | B13: Benefits enrollment window and effective dates confirmed | C13: Benefits | D13: -7 | E13: =IF(OR($D$2="",$D13=""),"",$D$2+$D13)
A14: Pre-start | B14: Day-one agenda sent to hiring manager; buddy/mentor assigned | C14: Coordinator | D14: -5 | E14: =IF(OR($D$2="",$D14=""),"",$D$2+$D14)
A15: Pre-start | B15: First-day logistics confirmed to new hire (time, place, contact, dress, what to bring) | C15: Coordinator | D15: -3 | E15: =IF(OR($D$2="",$D15=""),"",$D$2+$D15)
A16: Day one | B16: Greeting, workspace and equipment ready | C16: Manager | D16: 0 | E16: =IF(OR($D$2="",$D16=""),"",$D$2+$D16)
... A28: Audit | B28: Personnel / medical / eligibility files confirmed segregated and complete | C28: Coordinator | D28: 95 | E28: =IF(OR($D$2="",$D28=""),"",$D$2+$D28)
B30: Offsets are calendar days from the start date in D2. Verify the employment-eligibility deadline against current rules — it is stated in business days.

Sheet Timekeeping
A1: PHASE 4 — DAILY TIMEKEEPING EXCEPTIONS
A2: Work every exception the same day. Uncorrected time records create wage-and-hour exposure.
A4: Date | B4: Employee | C4: Location | D4: Shift | E4: Exception Type | F4: Detail | G4: Employee Contacted | H4: Supervisor Approval | I4: Correction Applied | J4: Reason | K4: Escalate? | L4: Closed Date | M4: Open Days
A5: 46248 | B5: R. Alvarez | C5: Memphis DC | D5: 2nd 3p-11p | E5: Missed meal break | F5: Punched 6h12m with no meal punch | G5: Yes | H5: Yes - supervisor T. Bell | I5: Meal premium applied | J5: System punch failure at kiosk 3 | K5: No | L5: 46248 | M5: =IF($A5="","",IF($L5="",TODAY()-$A5,$L5-$A5))
M6: =IF($A6="","",IF($L6="",TODAY()-$A6,$L6-$A6))
M7: =IF($A7="","",IF($L7="",TODAY()-$A7,$L7-$A7))
M8: =IF($A8="","",IF($L8="",TODAY()-$A8,$L8-$A8))
M9: =IF($A9="","",IF($L9="",TODAY()-$A9,$L9-$A9))
M10: =IF($A10="","",IF($L10="",TODAY()-$A10,$L10-$A10))
M11: =IF($A11="","",IF($L11="",TODAY()-$A11,$L11-$A11))
M12: =IF($A12="","",IF($L12="",TODAY()-$A12,$L12-$A12))
M13: =IF($A13="","",IF($L13="",TODAY()-$A13,$L13-$A13))
M14: =IF($A14="","",IF($L14="",TODAY()-$A14,$L14-$A14))
M15: =IF($A15="","",IF($L15="",TODAY()-$A15,$L15-$A15))
M16: =IF($A16="","",IF($L16="",TODAY()-$A16,$L16-$A16))
M17: =IF($A17="","",IF($L17="",TODAY()-$A17,$L17-$A17))
... M64: =IF($A64="","",IF($L64="",TODAY()-$A64,$L64-$A64))

Sheet ERLog
A1: PHASE 4 — EMPLOYEE RELATIONS INTAKE
A2: Facts only: date, participants, what was said, what was agreed. No diagnoses, no character judgments.
A4: Date | B4: Employee | C4: Location | D4: Category | E4: Summary (facts only — no conclusions) | F4: Classification | G4: Routed To | H4: Response Due | I4: Days to Due | J4: Closed Date | K4: Outcome
A5: 46245 | B5: [Employee] | C5: Memphis DC | D5: Pay / payroll question | E5: Associate states 8/2 shift differential not reflected on 8/8 pay statement. Supervisor confirms shift worked 3p-11p. | F5: Route | G5: Payroll | H5: 46247 | I5: =IF($H5="","",IF($J5<>"","Closed",$H5-TODAY())) | J5: 46247 | K5: Differential corrected on off-cycle; associate notified. EXAMPLE ROW — delete.
I6: =IF($H6="","",IF($J6<>"","Closed",$H6-TODAY()))
I7: =IF($H7="","",IF($J7<>"","Closed",$H7-TODAY()))
I8: =IF($H8="","",IF($J8<>"","Closed",$H8-TODAY()))
I9: =IF($H9="","",IF($J9<>"","Closed",$H9-TODAY()))
I10: =IF($H10="","",IF($J10<>"","Closed",$H10-TODAY()))
I11: =IF($H11="","",IF($J11<>"","Closed",$H11-TODAY()))
I12: =IF($H12="","",IF($J12<>"","Closed",$H12-TODAY()))
I13: =IF($H13="","",IF($J13<>"","Closed",$H13-TODAY()))
I14: =IF($H14="","",IF($J14<>"","Closed",$H14-TODAY()))
I15: =IF($H15="","",IF($J15<>"","Closed",$H15-TODAY()))
I16: =IF($H16="","",IF($J16<>"","Closed",$H16-TODAY()))
I17: =IF($H17="","",IF($J17<>"","Closed",$H17-TODAY()))
... I64: =IF($H64="","",IF($J64<>"","Closed",$H64-TODAY()))
E66: Escalate immediately and stop handling: harassment, discrimination, retaliation, safety threats, wage & hour, accommodation/leave, substance issues, theft/fraud, or anything with a manager as the subject.

Sheet KPIs
A1: PHASE 5 — RECRUITING & HR SCORECARD
A2: A metric without a named bottleneck and a recommended action is not a report.
A4: KPI | B4: Definition | C4: Current | D4: Prior Period | E4: Target | F4: Variance vs Target | G4: Direction | H4: Status | I4: Bottleneck Note | J4: Recommended Action | K4: Owner
A5: Time to fill (days) | B5: Req open to offer accepted | E5: 35 | F5: =IF(OR($C5="",$E5=""),"",$C5-$E5) | G5: =IF(OR($C5="",$D5=""),"",IF($C5>$D5,"Up vs prior",IF($C5<$D5,"Down vs prior","Flat"))) | H5: =IF(OR($C5="",$E5=""),"",IF($C5<=$E5,"ON TARGET",IF($C5<=$E5*1.15,"WATCH","OFF TARGET")))
A6: Time to hire (days) | B6: First candidate contact to offer accepted | E6: 21 | F6: =IF(OR($C6="",$E6=""),"",$C6-$E6) | G6: =IF(OR($C6="",$D6=""),"",IF($C6>$D6,"Up vs prior",IF($C6<$D6,"Down vs prior","Flat"))) | H6: =IF(OR($C6="",$E6=""),"",IF($C6<=$E6,"ON TARGET",IF($C6<=$E6*1.15,"WATCH","OFF TARGET")))
A7: Cost per hire ($) | B7: Total recruiting spend / hires | E7: 1200 | F7: =IF(OR($C7="",$E7=""),"",$C7-$E7) | G7: =IF(OR($C7="",$D7=""),"",IF($C7>$D7,"Up vs prior",IF($C7<$D7,"Down vs prior","Flat"))) | H7: =IF(OR($C7="",$E7=""),"",IF($C7<=$E7,"ON TARGET",IF($C7<=$E7*1.15,"WATCH","OFF TARGET")))
A8: Offer acceptance rate (%) | B8: Accepted / extended | E8: 88 | F8: =IF(OR($C8="",$E8=""),"",$C8-$E8) | G8: =IF(OR($C8="",$D8=""),"",IF($C8>$D8,"Up vs prior",IF($C8<$D8,"Down vs prior","Flat"))) | H8: =IF(OR($C8="",$E8=""),"",IF($C8>=$E8,"ON TARGET",IF($C8>=$E8*0.85,"WATCH","OFF TARGET")))
A9: Funnel: screen to interview (%) | B9: Interviewed / screened | E9: 45 | F9: =IF(OR($C9="",$E9=""),"",$C9-$E9) | G9: =IF(OR($C9="",$D9=""),"",IF($C9>$D9,"Up vs prior",IF($C9<$D9,"Down vs prior","Flat"))) | H9: =IF(OR($C9="",$E9=""),"",IF($C9>=$E9,"ON TARGET",IF($C9>=$E9*0.85,"WATCH","OFF TARGET")))
A10: Funnel: interview to offer (%) | B10: Offered / interviewed | E10: 30 | F10: =IF(OR($C10="",$E10=""),"",$C10-$E10) | G10: =IF(OR($C10="",$D10=""),"",IF($C10>$D10,"Up vs prior",IF($C10<$D10,"Down vs prior","Flat"))) | H10: =IF(OR($C10="",$E10=""),"",IF($C10>=$E10,"ON TARGET",IF($C10>=$E10*0.85,"WATCH","OFF TARGET")))
A11: Interview scheduling accuracy (%) | B11: Held as first scheduled / total | E11: 90 | F11: =IF(OR($C11="",$E11=""),"",$C11-$E11) | G11: =IF(OR($C11="",$D11=""),"",IF($C11>$D11,"Up vs prior",IF($C11<$D11,"Down vs prior","Flat"))) | H11: =IF(OR($C11="",$E11=""),"",IF($C11>=$E11,"ON TARGET",IF($C11>=$E11*0.85,"WATCH","OFF TARGET")))
A12: Candidate satisfaction (NPS) | B12: Post-process survey, all outcomes | E12: 40 | F12: =IF(OR($C12="",$E12=""),"",$C12-$E12) | G12: =IF(OR($C12="",$D12=""),"",IF($C12>$D12,"Up vs prior",IF($C12<$D12,"Down vs prior","Flat"))) | H12: =IF(OR($C12="",$E12=""),"",IF($C12>=$E12,"ON TARGET",IF($C12>=$E12*0.85,"WATCH","OFF TARGET")))
A13: Interviewer load (per wk) | B13: Interviews per interviewer per week | E13: 4 | F13: =IF(OR($C13="",$E13=""),"",$C13-$E13) | G13: =IF(OR($C13="",$D13=""),"",IF($C13>$D13,"Up vs prior",IF($C13<$D13,"Down vs prior","Flat"))) | H13: =IF(OR($C13="",$E13=""),"",IF($C13<=$E13,"ON TARGET",IF($C13<=$E13*1.15,"WATCH","OFF TARGET")))
A14: Quality of hire (%) | B14: 90-day retention x manager rating threshold | E14: 85 | F14: =IF(OR($C14="",$E14=""),"",$C14-$E14) | G14: =IF(OR($C14="",$D14=""),"",IF($C14>$D14,"Up vs prior",IF($C14<$D14,"Down vs prior","Flat"))) | H14: =IF(OR($C14="",$E14=""),"",IF($C14>=$E14,"ON TARGET",IF($C14>=$E14*0.85,"WATCH","OFF TARGET")))
A15: Early attrition (%) | B15: Separations within 90 days | E15: 8 | F15: =IF(OR($C15="",$E15=""),"",$C15-$E15) | G15: =IF(OR($C15="",$D15=""),"",IF($C15>$D15,"Up vs prior",IF($C15<$D15,"Down vs prior","Flat"))) | H15: =IF(OR($C15="",$E15=""),"",IF($C15<=$E15,"ON TARGET",IF($C15<=$E15*1.15,"WATCH","OFF TARGET")))
A16: Absence rate (%) | B16: Absent hours / scheduled hours | E16: 4 | F16: =IF(OR($C16="",$E16=""),"",$C16-$E16) | G16: =IF(OR($C16="",$D16=""),"",IF($C16>$D16,"Up vs prior",IF($C16<$D16,"Down vs prior","Flat"))) | H16: =IF(OR($C16="",$E16=""),"",IF($C16<=$E16,"ON TARGET",IF($C16<=$E16*1.15,"WATCH","OFF TARGET")))
A17: Voluntary turnover (%) | B17: Annualized voluntary separations | E17: 25 | F17: =IF(OR($C17="",$E17=""),"",$C17-$E17) | G17: =IF(OR($C17="",$D17=""),"",IF($C17>$D17,"Up vs prior",IF($C17<$D17,"Down vs prior","Flat"))) | H17: =IF(OR($C17="",$E17=""),"",IF($C17<=$E17,"ON TARGET",IF($C17<=$E17*1.15,"WATCH","OFF TARGET")))
A18: Vacancy rate (%) | B18: Open reqs / budgeted headcount | E18: 5 | F18: =IF(OR($C18="",$E18=""),"",$C18-$E18) | G18: =IF(OR($C18="",$D18=""),"",IF($C18>$D18,"Up vs prior",IF($C18<$D18,"Down vs prior","Flat"))) | H18: =IF(OR($C18="",$E18=""),"",IF($C18<=$E18,"ON TARGET",IF($C18<=$E18*1.15,"WATCH","OFF TARGET")))
A20: Targets in column E are placeholders — replace with your own. Note sample size where small; do not draw conclusions from a handful of hires.

Sheet Compliance
A1: PHASE 5 — COMPLIANCE & FILING CALENDAR
A2: Deadlines, thresholds and form versions change. Verify each item against the current rule before relying on it.
A4: Item | B4: Scope / Jurisdiction | C4: Frequency | D4: Next Due | E4: Days Until | F4: Flag | G4: Owner | H4: Status | I4: Verification Note
A5: Injury & illness log maintained (OSHA 300) | B5: US establishments | C5: Ongoing | E5: =IF($D5="","",$D5-TODAY()) | F5: =IF($D5="","",IF($H5="Complete","Closed",IF($E5<0,"OVERDUE",IF($E5<=30,"DUE SOON","OK")))) | I5: Verify recordability criteria and covered-establishment thresholds against current OSHA rules.
A6: Annual summary posted (OSHA 300A) | B6: US establishments | C6: Annual — posted Feb 1 to Apr 30 | E6: =IF($D6="","",$D6-TODAY()) | F6: =IF($D6="","",IF($H6="Complete","Closed",IF($E6<0,"OVERDUE",IF($E6<=30,"DUE SOON","OK")))) | I6: Confirm current posting window and signature requirements.
A7: Electronic injury data submission | B7: Covered US establishments | C7: Annual | E7: =IF($D7="","",$D7-TODAY()) | F7: =IF($D7="","",IF($H7="Complete","Closed",IF($E7<0,"OVERDUE",IF($E7<=30,"DUE SOON","OK")))) | I7: Confirm covered size/industry thresholds and the current submission deadline.
A8: BLS Survey of Occupational Injuries and Illnesses | B8: If sampled | C8: As sampled | E8: =IF($D8="","",$D8-TODAY()) | F8: =IF($D8="","",IF($H8="Complete","Closed",IF($E8<0,"OVERDUE",IF($E8<=30,"DUE SOON","OK")))) | I8: Respond by the deadline on the notice, from the maintained log.
A9: EEO-1 component filing | B9: Covered US employers | C9: Annual | E9: =IF($D9="","",$D9-TODAY()) | F9: =IF($D9="","",IF($H9="Complete","Closed",IF($E9<0,"OVERDUE",IF($E9<=30,"DUE SOON","OK")))) | I9: Confirm the current filing window; it has shifted in recent years.
A10: ACA reporting (1094-C / 1095-C) | B10: Applicable large employers | C10: Annual | E10: =IF($D10="","",$D10-TODAY()) | F10: =IF($D10="","",IF($H10="Complete","Closed",IF($E10<0,"OVERDUE",IF($E10<=30,"DUE SOON","OK")))) | I10: Coordinate with Benefits/Payroll; confirm furnishing and filing dates.
A11: Affirmative action plan obligations | B11: Covered federal contractors | C11: Annual | E11: =IF($D11="","",$D11-TODAY()) | F11: =IF($D11="","",IF($H11="Complete","Closed",IF($E11<0,"OVERDUE",IF($E11<=30,"DUE SOON","OK")))) | I11: Confirm coverage before assuming applicability.
A12: State pay-data reporting | B12: State-specific | C12: Annual | E12: =IF($D12="","",$D12-TODAY()) | F12: =IF($D12="","",IF($H12="Complete","Closed",IF($E12<0,"OVERDUE",IF($E12<=30,"DUE SOON","OK")))) | I12: Requirements vary by state; verify each operating state.
A13: Workplace poster currency audit | B13: All locations | C13: Semi-annual | E13: =IF($D13="","",$D13-TODAY()) | F13: =IF($D13="","",IF($H13="Complete","Closed",IF($E13<0,"OVERDUE",IF($E13<=30,"DUE SOON","OK")))) | I13: Federal, state and local posters; confirm current versions.
A14: Employment-eligibility file retention purge | B14: All locations | C14: Annual | E14: =IF($D14="","",$D14-TODAY()) | F14: =IF($D14="","",IF($H14="Complete","Closed",IF($E14<0,"OVERDUE",IF($E14<=30,"DUE SOON","OK")))) | I14: Retention is measured from hire and separation; verify the current formula.
A15: Personnel file completeness & segregation audit | B15: All locations | C15: Quarterly | E15: =IF($D15="","",$D15-TODAY()) | F15: =IF($D15="","",IF($H15="Complete","Closed",IF($E15<0,"OVERDUE",IF($E15<=30,"DUE SOON","OK")))) | I15: Confirm personnel / medical-ADA-leave / eligibility files remain separate.
A16: Background-check disclosure & authorization audit | B16: All locations | C16: Annual | E16: =IF($D16="","",$D16-TODAY()) | F16: =IF($D16="","",IF($H16="Complete","Closed",IF($E16<0,"OVERDUE",IF($E16<=30,"DUE SOON","OK")))) | I16: Standalone disclosure; confirm ban-the-box and fair-chance rules per jurisdiction.
... A18: Minor work permits and hours restrictions | B18: Locations employing minors | C18: Ongoing | E18: =IF($D18="","",$D18-TODAY()) | F18: =IF($D18="","",IF($H18="Complete","Closed",IF($E18<0,"OVERDUE",IF($E18<=30,"DUE SOON","OK")))) | I18: Hour and task restrictions vary by state and by school session.

Sheet Restricted
A1: RESTRICTED — LIMITED ACCESS
A2: Compensation and background-check status. Do not merge these fields into Reqs, Candidates or Offers, and do not share this tab in a group thread or an open folder.
A4: Cand ID | B4: Req ID | C4: Approved Range Min | D4: Approved Range Max | E4: Offer Base | F4: Within Range? | G4: Sign-on / Premium | H4: Background Status | I4: Adverse Action Stage | J4: Approver
A5: C-2207 | B5: REQ-1041 | C5: 58000 | D5: 66000 | E5: 62000 | F5: =IF(OR($E5="",$C5="",$D5=""),"",IF(AND($E5>=$C5,$E5<=$D5),"In range","OUT OF RANGE - approval required")) | G5: None | H5: Pending | I5: N/A | J5: A. Reyes
F6: =IF(OR($E6="",$C6="",$D6=""),"",IF(AND($E6>=$C6,$E6<=$D6),"In range","OUT OF RANGE - approval required"))
F7: =IF(OR($E7="",$C7="",$D7=""),"",IF(AND($E7>=$C7,$E7<=$D7),"In range","OUT OF RANGE - approval required"))
F8: =IF(OR($E8="",$C8="",$D8=""),"",IF(AND($E8>=$C8,$E8<=$D8),"In range","OUT OF RANGE - approval required"))
F9: =IF(OR($E9="",$C9="",$D9=""),"",IF(AND($E9>=$C9,$E9<=$D9),"In range","OUT OF RANGE - approval required"))
F10: =IF(OR($E10="",$C10="",$D10=""),"",IF(AND($E10>=$C10,$E10<=$D10),"In range","OUT OF RANGE - approval required"))
F11: =IF(OR($E11="",$C11="",$D11=""),"",IF(AND($E11>=$C11,$E11<=$D11),"In range","OUT OF RANGE - approval required"))
F12: =IF(OR($E12="",$C12="",$D12=""),"",IF(AND($E12>=$C12,$E12<=$D12),"In range","OUT OF RANGE - approval required"))
F13: =IF(OR($E13="",$C13="",$D13=""),"",IF(AND($E13>=$C13,$E13<=$D13),"In range","OUT OF RANGE - approval required"))
F14: =IF(OR($E14="",$C14="",$D14=""),"",IF(AND($E14>=$C14,$E14<=$D14),"In range","OUT OF RANGE - approval required"))
F15: =IF(OR($E15="",$C15="",$D15=""),"",IF(AND($E15>=$C15,$E15<=$D15),"In range","OUT OF RANGE - approval required"))
F16: =IF(OR($E16="",$C16="",$D16=""),"",IF(AND($E16>=$C16,$E16<=$D16),"In range","OUT OF RANGE - approval required"))
F17: =IF(OR($E17="",$C17="",$D17=""),"",IF(AND($E17>=$C17,$E17<=$D17),"In range","OUT OF RANGE - approval required"))
... F44: =IF(OR($E44="",$C44="",$D44=""),"",IF(AND($E44>=$C44,$E44<=$D44),"In range","OUT OF RANGE - approval required"))
A46: Background checks run only after a conditional offer, on standalone written disclosure and authorization. Any adverse finding goes to HRBP / Employment Counsel before any letter is issued.
